findmycells/__init__.py
findmycells/_modidx.py
findmycells/configs.py
findmycells/core.py
findmycells/database.py
findmycells/interfaces.py
findmycells/utils.py
findmycells/inspection/__init__.py
findmycells/inspection/methods.py
findmycells/postprocessing/__init__.py
findmycells/postprocessing/specs.py
findmycells/postprocessing/strategies.py
findmycells/preprocessing/__init__.py
findmycells/preprocessing/specs.py
findmycells/preprocessing/strategies.py
findmycells/quantification/__init__.py
findmycells/quantification/specs.py
findmycells/quantification/strategies.py
findmycells/readers/__init__.py
findmycells/readers/microscopy_images.py
findmycells/readers/rois.py
findmycells/readers/specs.py
findmycells/segmentation/__init__.py
findmycells/segmentation/specs.py
findmycells/segmentation/strategies.py
findmycells-1.0.0.dist-info/LICENSE
findmycells-1.0.0.dist-info/METADATA
findmycells-1.0.0.dist-info/WHEEL
findmycells-1.0.0.dist-info/entry_points.txt
findmycells-1.0.0.dist-info/top_level.txt
findmycells-1.0.0.dist-info/RECORD
