Metadata-Version: 2.1
Name: findmycells
Version: 1.0.0
Summary: An end-to-end bioimage analysis pipeline with state-of-the-art tools for non-coding experts
Home-page: https://github.com/Defense-Circuits-Lab/findmycells
Author: DSegebarth
Author-email: d.segebarth@gmail.com
License: GNU General Public License v3
Keywords: nbdev jupyter notebook python
Classifier: Development Status :: 4 - Beta
Classifier: Intended Audience :: Developers
Classifier: Natural Language :: English
Classifier: Programming Language :: Python :: 3.9
Classifier: Programming Language :: Python :: 3.10
Classifier: License :: OSI Approved :: GNU General Public License v3 (GPLv3)
Requires-Python: >=3.9
License-File: LICENSE
Requires-Dist: shapely (==2.0.6)
Requires-Dist: ipywidgets (==7.6.5)
Requires-Dist: jupyterlab
Requires-Dist: imageio (==2.21.3)
Requires-Dist: scikit-image (==0.19.3)
Requires-Dist: scikit-learn (==1.5.2)
Requires-Dist: matplotlib (==3.9.2)
Requires-Dist: contourpy (==1.3)
Requires-Dist: scipy (<1.15)
Requires-Dist: deepflash2 (==0.1.7)
Requires-Dist: albumentations (==1.2.1)
Requires-Dist: cellpose (==2.0.5)
Requires-Dist: czifile
Requires-Dist: roifile (==2024.9.15)
Requires-Dist: connected-components-3d
Requires-Dist: ipyfilechooser
Requires-Dist: wget
Requires-Dist: jupyterlab-widgets (==1.0.2)
Requires-Dist: pandas (==1.4.0)
Requires-Dist: fastcore (==1.5.27)
Requires-Dist: numpy (==1.26.4)
Requires-Dist: notebook (==6.1.5)
Requires-Dist: opencv-python (<4.11)
Requires-Dist: openpyxl (==3.1.5)
Provides-Extra: dev
Requires-Dist: nbdev ; extra == 'dev'
